Workbook

Sheet FS Balance Sheet 2026
A4: Balance Sheet
A5: 46265
A6: Assets
B8: Current Assets
C9: Cash and Cash Equivalents | E9: =SUM('August 2026 - Balance Sheet'!E11:E11) -> 10056039
C10: Contract Receivables | E10: =SUM('August 2026 - Balance Sheet'!E12)-'August 2026 -AR Aging'!F441 -> 22228480
C11: Other Receivables | E11: =SUM('August 2026 - Balance Sheet'!E13) -> 337927.71
C12: Prepaid Expenses and Other Current Assets | E12: =SUM('August 2026 - Balance Sheet'!E41:E45,'August 2026 - Balance Sheet'!E15) -> 765744.18
C13: Contract Assets* | E13: =SUM('August 2026 - Balance Sheet'!E14+'August 2026 - Over Under Report'!P85+'August 2026 -AR Aging'!F441) -> -4021061.7
C16: Total Current Assets: | E16: =SUM(E9:E15) -> 29367129
B18: Property and Equipment
C20: Vehicles | E20: =SUM('August 2026 - Balance Sheet'!E21) -> 100000
C21: Office Equipment | E21: =SUM('August 2026 - Balance Sheet'!E22) -> 3772.74
C22: Furniture and Fixtures | E22: =SUM('August 2026 - Balance Sheet'!E24) -> 62228.65
C23: Less Accumulated Depreciation | E23: =SUM('August 2026 - Balance Sheet'!E30,'August 2026 - Balance Sheet'!E31,'August 2026 - Balance Sheet'!E33) -> -45959.8
C25: Total Property and Equipment | E25: =SUM(E20:E24) -> 120041.59
B27: Other Assets
C28: Software Costs, net of Accumulated Amortization | E28: =SUM('August 2026 - Balance Sheet'!E23,'August 2026 - Balance Sheet'!E32) -> 36000
D31: Total Assets: | E31: =SUM(E16,E25,E28) -> 29523170
A33: Liabilities
B35: Current Liabilities
C37: Accounts Payable | E37: =SUM('August 2026 - Balance Sheet'!E56) -> 3871881.6
C38: Accrued Liabilities | E38: =SUM('August 2026 - Balance Sheet'!E59:E67) -> 11423882
C39: Notes Payable | E39: =SUM('August 2026 - Balance Sheet'!E68) -> 0
C40: Distributions Payable | E40: ='August 2026 - Balance Sheet'!E58 -> 164495.96
C41: Contract Liabilities* | E41: =SUM('August 2026 - Balance Sheet'!E57+'August 2026 - Over Under Report'!P85) -> -7188881.2
C44: Total Current Liabilities | E44: =SUM(E37:E43) -> 8271378.5
B46: Notes Payable to Stockholders | E46: =SUM('August 2026 - Balance Sheet'!E74:E77) -> 1044085
C48: Total Liabilities | E48: =SUM(E44,E46) -> 9315463.5
B50: Stockholder's Equity
C51: Common Stock | E51: =SUM('August 2026 - Balance Sheet'!E87:E91) -> 1000
C52: Additional Paid-in Capital | E52: =SUM('August 2026 - Balance Sheet'!E92) -> 0
C53: Retained Earnings | E53: =SUM('August 2026 - Balance Sheet'!E93,'August 2026 - Balance Sheet'!E99)+'August 2026 - Inc. Stmt- ALL'!G130 -> 20206707
C54: Total Stockholder's Equity | E54: =SUM(E51:E53) -> 20207707
D56: Total Liabilities and Equity: | E56: =SUM(E48,E54) -> 29523170
E60: =E56-E31 -> 0

Sheet FS Stmt of Inc & RE- 2026
A7: Statement of Income and Retained Earnings
A8: January 1, 2026 - August 31, 2026
C10: 2026 | D10: 2019 | E10: 2018 | F10: 2017 | G10: 2016
A12: Contract Revenues | C12: =SUM('August 2026 - Inc. Stmt- ALL'!G17:G18) -> 64039629 | D12: 43843514 | E12: 50727670 | F12: 33398814 | G12: 19662807
A14: Costs of Contract Revenues | C14: =SUM('August 2026 - Inc. Stmt- ALL'!G35) -> 52485705 | D14: 40056194 | E14: 43612053 | F14: 29104212 | G14: 15862450
A16: Gross Profit | C16: =SUM(C12-C14) -> 11553924 | D16: 3787320.2 | E16: 7115616.9 | F16: 4294601.8 | G16: 3800357.5
A18: Operating Expenses | C18: ='August 2026 - Inc. Stmt- ALL'!G96+'August 2026 - Inc. Stmt- ALL'!G86-'August 2026 - Inc. Stmt- ALL'!G71+'August 2026 - Inc. Stmt- ALL'!G125+'August 2026 - Inc. Stmt- ALL'!G128 -> 2041561.7 | D18: 1497446 | E18: 1549793.3 | F18: 2457828.2 | G18: 2242522.8
A20: Income before Other Income (Expense) | C20: =SUM(C16-C18) -> 9512362.5 | D20: 2289874.2 | E20: 5565823.6 | F20: 1836773.7 | G20: 1557834.8
A22: Other Income (Expense)
B23: Interest Income | C23: =SUM('August 2026 - Inc. Stmt- ALL'!G113) -> 89971.27 | D23: 0 | E23: 0 | F23: 0 | G23: 0
B24: Miscellaneous Income | C24: ='August 2026 - Inc. Stmt- ALL'!G19+'August 2026 - Inc. Stmt- ALL'!G110+'August 2026 - Inc. Stmt- ALL'!G111+'August 2026 - Inc. Stmt- ALL'!G112+'August 2026 - Inc. Stmt- ALL'!G114 -> 188235.87 | D24: 619186.78 | E24: 40284.15 | F24: 29891.49 | G24: 53610.93
B25: Interest Expense | C25: =SUM('August 2026 - Inc. Stmt- ALL'!G71)*-1 -> -44085.42 | D25: -121829.35 | E25: -121542.34 | F25: -76540.68 | G25: -76540.68
B27: Total Other Income (Expense) | C27: =SUM(C23:C25) -> 234121.72 | D27: 497357.43 | E27: -81258.19 | F27: -46649.19 | G27: -22929.75
B29: Net Income Before Tax: | C29: =+#REF!+C27-#REF!-#REF!-#REF! -> #REF! | D29: #REF! | E29: #REF! | F29: #REF! | G29: #REF!
B31: Net Income: | C31: =SUM(C20,C27) -> 9746484.2 | D31: 2787231.7 | E31: 5484565.4 | F31: 1790124.5 | G31: 1534905
B33: Retained Earnings at Beginning of Year | C33: =SUM('August 2026 - Balance Sheet'!E93) -> 11273709 | D33: 3711295.3 | E33: 1896859.7 | F33: 2676967.5 | G33: 1776331.2
B35: Less Distributions | C35: =-'August 2026 - Balance Sheet'!E101 -> 813486.15 | D35: 893096.63 | E35: 3670129.9 | F35: 782904.11 | G35: 634268.75
B38: Retained Earnings at End of Year (Period) | C38: =SUM(C31,C33)-C35 -> 20206707 | D38: 5605430.3 | E38: 3711295.3 | F38: 3684187.8 | G38: 2676967.5
F40: =SUM(F38-E33) -> 1787328.1
F41: D.Stowell Stock Redemption 1.1.18

Sheet August 2026 - Balance Sheet
A4: Balance Sheet
A5: 46265
A7: Assets
A9: Current Assets
B11: Truist Checking/JP Morgan Money Market | E11: 10056039
B12: Contract Receivables | E12: 22228480 | K12: 11501
B13: Other Receivables | E13: 337927.71
B14: Underbillings | E14: 3167819.5
B15: Payroll Advances | E15: 0
C17: Total Current Assets: | F17: =+SUM(E11:E15) -> 35790266
A19: Long Term Assets
B21: Vehicles | E21: 100000
B22: Office Equipment | E22: 3772.74
B23: Software | E23: 54000
B24: Furniture and Fixtures | E24: 62228.65
C26: Total Long Term Assets: | E26: =+SUM(E21:E24) -> 220001.39
A28: Accumulated Depreciation
B30: Accum Dep'n Vehicles | E30: -33333.4
B31: Accum Dep'n Office Equipment | E31: -3772.74
B32: Accum Amort Software | E32: -18000
B33: Accum Dep'n Furniture & Fxt | E33: -8853.66
C35: Total Accumulated Depreciation: | E35: =+SUM(E30:E33) -> -63959.8
C37: Net Long Term Assets: | F37: =+E26-ABS(E35) -> 156041.59
A39: Other Assets
B41: Prepaid Insurance - 2019 | E41: 58572.08
B42: Prepaid Ins.- Sub. Acct. 2013 | E42: 106789.47
B43: Life Insurance - Employee | E43: 571107.25
B44: Term Life Ins. - Employee | E44: 1071
B45: Prepaid Expenses | E45: 28204.38
C47: Total Other Assets: | F47: =+SUM(E41:E45) -> 765744.18
D49: Total Assets: | F49: =+(+F17+F47+E26)-ABS(E35) -> 36712052
A52: Liabilities
A54: Current Liabilities
B56: Trade Accounts Payable | E56: 3871881.6
B57: Other Accounts Payable
B58: Distributions Payable - SH | E58: 164495.96
B59: Overbillings | E59: 11194804
B60: Fica/FIT Payable | E60: 0
B61: Sales Taxes Payable | E61: 5407.56
B62: TX SUI Payable | E62: 0
B63: 401K Payable | E63: 0
B64: Fl WC Payable | E64: 0
B65: Performance Bonus Payable | E65: 0
B66: Accrued Expense | E66: 0
B67: Credit Cards | E67: 223670.36
B68: Truist LOC | E68: 0
C70: Total Current Liabilities: | F70: =+SUM(E56:E68) -> 15460260
A72: Long Term Liabilities
B74: Interest Pay | E74: 0
B75: Other Notes Payable | E75: 0
B76: Shareholder Pay - Shumaker | E76: 44085.03
B77: S/H Notes Payable-WS | E77: 1000000
C79: Total Long Term Liabilities: | F79: =+SUM(E74:E77) -> 1044085
D81: Total Liabilities: | F81: =+F70+F79 -> 16504345
A83: Equity
A85: Equity/Capital
B87: Capital Stock - Shumaker | E87: 730
B88: Capital Stock - Bishop | E88: 50
B89: Capital Stock - Cassell | E89: 100
B90: Capital Stock - VanHouten | E90: 100
B91: Capital Stock - Flynn | E91: 20
B92: Additional Paid-in Capital | E92: 0
B93: Retained Earnings | E93: 11273709
C95: Subtotal Equity/Capital: | E95: =SUM(E87:E93) -> 11274709
A97: Owner's Drawing/Dividend
B99: Shareholder Distributions | E99: -813486.15
C101: Total Owner's Drawing/Dividend: | E101: =+SUM(E99:E99) -> -813486.15
A103: Current Profit (Loss): | E103: =SUM('August 2026 - Inc. Stmt- ALL'!G120)-'August 2026 - Inc. Stmt- ALL'!G125-'August 2026 - Inc. Stmt- ALL'!G128 -> 9746484.2
D105: Total Equity/Capital: | F105: =+E95+E101+E103 -> 20207707
D107: Total Liabilities + Equity: | F107: =+(F70+F79+E95)+E101+E103 -> 36712052
F110: =F107-F49 -> 0

Sheet August 2026 - Inc. Stmt- ALL
A7: Income Statement - All Departments
A8: 46265
N10: 45900
E11: Over/Under | F11: Over/Under | I11: Over/Under | J11: Over/Under | N11: Prior Year
C12: Period | D12: Budget | E12: Budget % - Period | F12: Budget - Period | G12: YTD | H12: Budget | I12: Budget % - YTD | J12: Budget - YTD | K12: 2026 BUDGET | N12: YTD | O12: Var
S13: YTD Months | T13: 8
A15: Operating Income
B17: Contract Income | C17: 8306017.2 | D17: =SUM(K17/12) -> 6666666.7 | F17: =SUM(C17-D17) -> 1639350.6 | G17: 61018486 | H17: =SUM(D17*T$13) -> 53333333 | J17: =SUM(G17-H17) -> 7685152.6 | K17: =K21 -> 80000000
B18: Over/Underbillings | C18: -338708.68 | D18: 0 | G18: 3021143.1 | H18: =SUM(D18*T$13) -> 0
B19: Discounts Earned | C19: 22205.49 | D19: 0 | G19: 193081.97 | H19: =SUM(D19*T$13) -> 0
B21: Total Operating Income: | C21: =SUM(C17:C20) -> 7989514.1 | D21: =SUM(D17:D20) -> 6666666.7 | E21: =((C21-D21)/D21)*100 -> 19.842711 | F21: =SUM(C21-D21) -> 1322847.4 | G21: =SUM(G17:G20) -> 64232711 | H21: =SUM(H17:H20) -> 53333333 | I21: =((G21-H21)/H21)*100 -> 20.436333 | J21: =SUM(G21-H21) -> 10899378 | K21: 80000000 | N21: 48256343 | O21: =G21-N21 -> 15976368
A23: Direct Expense
B25: Material | C25: 1351245.8 | D25: 0 | G25: 15541061 | H25: =SUM(D25*T$13) -> 0
B26: Equipment Expense | C26: 173046.29 | D26: 0 | G26: 2670010.6 | H26: =SUM(D26*T$13) -> 0
B27: Subcontracted | C27: 3306313.5 | D27: 0 | G27: 26829372 | H27: =SUM(D27*T$13) -> 0
B28: Other Job Expense | C28: 232181.83 | D28: 0 | G28: 2623558.7 | H28: =SUM(D28*T$13) -> 0
B29: Direct Labor | C29: 562355.92 | D29: 0 | G29: 4350728 | H29: =SUM(D29*T$13) -> 0
B30: D/L Payroll Taxes | C30: 36959.76 | D30: 0 | G30: 302849.51 | H30: =SUM(D30*T$13) -> 0
B31: D/L Workers' Compensation | C31: 4146.39 | D31: 0 | G31: 30050.81 | H31: =SUM(D31*T$13) -> 0
B32: D/L Benefits | C32: 0 | D32: 0 | G32: 138074.05 | H32: =SUM(D32*T$13) -> 0
B35: Total Direct Expense: | C35: =SUM(C25:C34) -> 5666249.5 | D35: =SUM(D17*0.8468) -> 5645333.3 | E35: =((C35-D35)/D35) -> 0.0037050366 | F35: =SUM(C35-D35) -> 20916.167 | G35: =SUM(G25:G34) -> 52485705 | H35: =K35/12*T13 -> 45164445 | I35: =((G35-H35)/H35) -> 0.1621023 | J35: =H35-G35 -> -7321260.2 | K35: 67746667 | N35: 41029273 | O35: =N35-G35 -> -11456432
B38: Total Direct & Equip/Shop Expense: | C38: =SUM(C35) -> 5666249.5 | D38: 0 | G38: =SUM(G35) -> 52485705 | H38: =H35 -> 45164445 | K38: =K35 -> 67746667
B40: Gross Profit: | C40: =+C21-C35 -> 2323264.6 | D40: =+D21-D35 -> 1021333.3 | G40: =+G21-G35 -> 11747006 | H40: =+H21-H35 -> 8168888.7 | J40: =G40-H40 -> 3578117.5 | K40: =+K21-K35 -> 12253333 | N40: =N21-N35 -> 7227069.7 | O40: =G40-N40 -> 4519936.5
B42: % Operating Income: | C42: =SUM(C40/C21)*100% -> 0.29078922 | D42: =SUM(D40/D21)*100% -> 0.1532 | G42: =SUM(G40/G21)*100% -> 0.18288199 | H42: =SUM(H40/H21)*100% -> 0.15316666 | K42: =SUM(K40/K21)*100% -> 0.15316666 | N42: =N40/N21 -> 0.14976414
A44: Overhead Expense
B46: Rent | C46: 17342.58 | D46: =SUM(K46/12) -> 20143.39 | F46: =SUM(C46-D46) -> -2800.81 | G46: 154110.28 | H46: =SUM(D46*T$13) -> 161147.12 | J46: =H46-G46 -> 7036.84 | K46: 241720.68
B47: Office Supplies | C47: 0 | D47: =SUM(K47/12) -> 1500 | F47: =SUM(C47-D47) -> -1500 | G47: -114.16 | H47: =SUM(D47*T$13) -> 12000 | J47: =H47-G47 -> 12114.16 | K47: 18000
B48: Office Expense | C48: 143531.77 | D48: =SUM(K48/12) -> 6250 | F48: =SUM(C48-D48) -> 137281.77 | G48: 237962.9 | H48: =SUM(D48*T$13) -> 50000 | J48: =H48-G48 -> -187962.9 | K48: 75000
B49: Utilities | C49: 433.32 | D49: =SUM(K49/12) -> 1033.8333 | F49: =SUM(C49-D49) -> -600.51333 | G49: 6329.86 | H49: =SUM(D49*T$13) -> 8270.6667 | J49: =H49-G49 -> 1940.8067 | K49: 12406
B50: Telephone | C50: 343.38 | D50: =SUM(K50/12) -> 489.16667 | F50: =SUM(C50-D50) -> -145.78667 | G50: 2901.3 | H50: =SUM(D50*T$13) -> 3913.3333 | J50: =H50-G50 -> 1012.0333 | K50: 5870
B51: Cellular Phone | C51: 1805.88 | D51: =SUM(K51/12) -> 2566.6667 | F51: =SUM(C51-D51) -> -760.78667 | G51: 18165.71 | H51: =SUM(D51*T$13) -> 20533.333 | J51: =H51-G51 -> 2367.6233 | K51: 30800
B52: IT Services | C52: 2435 | D52: =SUM(K52/12) -> 2941.6667 | F52: =SUM(C52-D52) -> -506.66667 | G52: 108020 | H52: =SUM(D52*T$13) -> 23533.333 | J52: =H52-G52 -> -84486.667 | K52: 35300
B53: Internet Service | C53: 1334.06 | D53: =SUM(K53/12) -> 1295 | F53: =SUM(C53-D53) -> 39.06 | G53: 10501.5 | H53: =SUM(D53*T$13) -> 10360 | J53: =H53-G53 -> -141.5 | K53: 15540
B54: Bank Charges | C54: 329.13 | D54: =SUM(K54/12) -> 1131.4167 | F54: =SUM(C54-D54) -> -802.28667 | G54: 1049.32 | H54: =SUM(D54*T$13) -> 9051.3333 | J54: =H54-G54 -> 8002.0133 | K54: 13577
B55: Postage and Freight | C55: 753.94 | D55: =SUM(K55/12) -> 572.75 | F55: =SUM(C55-D55) -> 181.19 | G55: 3107.39 | H55: =SUM(D55*T$13) -> 4582 | J55: =H55-G55 -> 1474.61 | K55: 6873
B56: Janitorial | C56: 470 | D56: =SUM(K56/12) -> 541.66667 | F56: =SUM(C56-D56) -> -71.666667 | G56: 4170 | H56: =SUM(D56*T$13) -> 4333.3333 | J56: =H56-G56 -> 163.33333 | K56: 6500
B57: Advertising and Promotion | C57: 0 | D57: =SUM(K57/12) -> 17.416667 | F57: =SUM(C57-D57) -> -17.416667 | G57: 12126.35 | H57: =SUM(D57*T$13) -> 139.33333 | J57: =H57-G57 -> -11987.017 | K57: 209
... B68: Charity Donations | C68: 0 | D68: =SUM(K68/12) -> 1058 | F68: =SUM(C68-D68) -> -1058 | G68: 6645.08 | H68: =SUM(D68*T$13) -> 8464 | J68: =H68-G68 -> 1818.92 | K68: 12696
B69: General Insurance /Life | C69: 0 | D69: =SUM(K69/12) -> 5602 | F69: =SUM(C69-D69) -> -5602 | G69: 18566.33 | H69: =SUM(D69*T$13) -> 44816 | J69: =H69-G69 -> 26249.67 | K69: =43192+24032 -> 67224
B70: Taxes and Licenses | C70: 0 | D70: =SUM(K70/12) -> 24.833333 | F70: =SUM(C70-D70) -> -24.833333 | G70: 453.4 | H70: =SUM(D70*T$13) -> 198.66667 | J70: =H70-G70 -> -254.73333 | K70: 298
B71: Interest Expense | C71: 4166.67 | D71: =SUM(K71/12) -> 8333 | F71: =SUM(C71-D71) -> -4166.33 | G71: 44085.42 | H71: =SUM(D71*T$13) -> 66664 | J71: =H71-G71 -> 22578.58 | K71: 99996
B72: Plan Fees | C72: 0 | D72: =SUM(K72/12) -> 0 | F72: =SUM(C72-D72) -> 0 | G72: 0 | H72: =SUM(D72*T$13) -> 0 | J72: =H72-G72 -> 0
B73: Bonding Fees | C73: 0 | D73: =SUM(K73/12) -> 989.66667 | F73: =SUM(C73-D73) -> -989.66667 | G73: 0 | H73: =SUM(D73*T$13) -> 7917.3333 | J73: =H73-G73 -> 7917.3333 | K73: 11876
B74: Overhead Labor | C74: -87943.12 | D74: =SUM(K74/12) -> 18171.083 | F74: =SUM(C74-D74) -> -106114.2 | G74: 37059.94 | H74: =SUM(D74*T$13) -> 145368.67 | J74: =H74-G74 -> 108308.73 | K74: 218053
B75: FL O/H Payroll Taxes | C75: -7379.58 | D75: =SUM(K75/12) -> 4169.6667 | F75: =SUM(C75-D75) -> -11549.247 | G75: 20469.68 | H75: =SUM(D75*T$13) -> 33357.333 | J75: =H75-G75 -> 12887.653 | K75: 50036
B76: FL O/H Workers' Compensation | C76: 188.92 | D76: =SUM(K76/12) -> 175 | F76: =SUM(C76-D76) -> 13.92 | G76: 1372.83 | H76: =SUM(D76*T$13) -> 1400 | J76: =H76-G76 -> 27.17 | K76: 2100
B77: O/H Benefits | C77: 9639.44 | D77: =SUM(K77/12) -> 6077.665 | F77: =SUM(C77-D77) -> 3561.775 | G77: 50001.15 | H77: =SUM(D77*T$13) -> 48621.32 | J77: =H77-G77 -> -1379.83 | K77: 72931.98
B78: 401K Match | C78: 14396.5 | D78: =SUM(K78/12) -> 14622.192 | F78: =SUM(C78-D78) -> -225.69167 | G78: 125413.33 | H78: =SUM(D78*T$13) -> 116977.53 | J78: =H78-G78 -> -8435.7967 | K78: 175466.3
B79: Other Vehicle Expense | C79: 4500 | D79: =SUM(K79/12) -> 4511 | F79: =SUM(C79-D79) -> -11 | G79: 36000 | H79: =SUM(D79*T$13) -> 36088 | J79: =H79-G79 -> 88 | K79: 54132
B80: Vehicle Depreciation Expense | C80: 1666.67 | D80: =SUM(K80/12) -> 1666.67 | F80: =SUM(C80-D80) -> 0 | G80: 13333.36 | H80: =SUM(D80*T$13) -> 13333.36 | J80: =H80-G80 -> 0 | K80: 20000.04
B81: Office Equipment Dep'n Expense | C81: 0 | D81: =SUM(K81/12) -> 0 | F81: =SUM(C81-D81) -> 0 | G81: 0 | H81: =SUM(D81*T$13) -> 0 | J81: =H81-G81 -> 0
B82: Furniture & Fixtures Dep'n Exp | C82: 1067.5 | D82: =SUM(K82/12) -> 1067.5 | F82: =SUM(C82-D82) -> 0 | G82: 8540 | H82: =SUM(D82*T$13) -> 8540 | J82: =H82-G82 -> 0 | K82: 12810
B83: Software Amort Exp | C83: 1500 | D83: =SUM(K83/12) -> 1500 | F83: =SUM(C83-D83) -> 0 | G83: 12000 | H83: =SUM(D83*T$13) -> 12000 | J83: =H83-G83 -> 0 | K83: 18000
B84: Marketing Expense | C84: 4234.65 | D84: =SUM(K84/12) -> 10683.333 | F84: =SUM(C84-D84) -> -6448.6833 | G84: 49294.91 | H84: =SUM(D84*T$13) -> 85466.667 | J84: =H84-G84 -> 36171.757 | K84: 128200
B86: Total Overhead Expense: | C86: =SUM(C46:C85) -> 194604.9 | D86: =SUM(D46:D85) -> 200081.25 | E86: =((C86-D86)/D86)*100 -> -2.7370631 | F86: =SUM(F46:F84) -> -5476.35 | G86: =SUM(G46:G85) -> 1596153.7 | H86: =SUM(H46:H85) -> 1600650 | I86: =((G86-H86)/H86)*100 -> -0.28090463 | J86: =SUM(J46:J84) -> 4496.3 | K86: =SUM(K46:K85) -> 2400975 | N86: =1493995.2-59258.1 -> 1434737.1 | O86: =N86-G86 -> -161416.6
B90: Admin Salaries | C90: 39325.35 | D90: =SUM(K90/12) -> 62730.893 | F90: =SUM(C90-D90) -> -23405.543 | G90: 413605.82 | H90: =SUM(D90*T$13) -> 501847.15 | J90: =H90-G90 -> 88241.327 | K90: 752770.72
B91: Admin Payroll Taxes | C91: 3429.56 | D91: =SUM(K91/12) -> 4005.1067 | F91: =SUM(C91-D91) -> -575.54667 | G91: 44242.91 | H91: =SUM(D91*T$13) -> 32040.853 | J91: =H91-G91 -> -12202.057 | K91: 48061.28
B92: Admin Worker's Compensation | C92: 51.83 | D92: =SUM(K92/12) -> 65.511465 | F92: =SUM(C92-D92) -> -13.681465 | G92: 484.64 | H92: =SUM(D92*T$13) -> 524.09172 | J92: =H92-G92 -> 39.451717 | K92: 786.13757
B93: Admin Benefits | C93: 2059.59 | D93: =SUM(K93/12) -> 6384.4525 | F93: =SUM(C93-D93) -> -4324.8625 | G93: 31160.08 | H93: =SUM(D93*T$13) -> 51075.62 | J93: =H93-G93 -> 19915.54 | K93: 76613.43
B94: Admin Liability Insurance | C94: 0 | D94: =SUM(K94/12) -> 0 | F94: =SUM(C94-D94) -> 0 | H94: =SUM(D94*T$13) -> 0 | J94: =H94-G94 -> 0
B96: Total Administrative Expense: | C96: =SUM(C90:C95) -> 44866.33 | D96: =SUM(D90:D95) -> 73185.964 | E96: =((C96-D96)/D96)*100 -> -38.695444 | F96: =SUM(F90:F94) -> -28319.634 | G96: =SUM(G90:G95) -> 489493.45 | H96: =SUM(H90:H95) -> 585487.71 | I96: =((G96-H96)/H96)*100 -> -16.395607 | J96: =SUM(J90:J94) -> 95994.262 | K96: =SUM(K90:K95) -> 878231.57 | N96: 564298.66 | O96: =N96-G96 -> 74805.21
B98: Total Indirect Expense: | C98: =+C86+C96 -> 239471.23 | D98: =+D86+D96 -> 273267.21 | E98: =+E86+E96 -> -41.432507 | F98: =+F86+F96 -> -33795.984 | G98: =+G86+G96 -> 2085647.1 | H98: =+H86+H96 -> 2186137.7 | I98: =+I86+I96 -> -16.676511 | J98: =+J86+J96 -> 100490.56 | K98: =SUM(K86,K96) -> 3279206.6 | N98: =N96+N86 -> 1999035.8 | O98: =N98-G98 -> -86611.39
B100: % Overhead Expense | C100: =SUM(C98/C21)*100% -> 0.029973191 | G100: =SUM(G98/G21)*100% -> 0.032470172 | K100: =SUM(K98/K17)*100% -> 0.040990082 | N100: =SUM(N98/N21)*100% -> 0.041425347
B102: Income from Operations: | C102: =+C21-C35-(C86+C96) -> 2083793.3 | G102: =+G21-G35-(G86+G96) -> 9661359 | H102: =K102/12*T13 -> 5982751 | J102: =G102-H102 -> 3678608.1 | K102: =+K21-K35-(K86+K96) -> 8974126.4 | N102: =N40-N98 -> 5228033.9 | O102: =G102-N102 -> 4433325.1
B104: % Operating Income | C104: =SUM(C102/C21)*100% -> 0.26081603 | G104: =SUM(G102/G21)*100% -> 0.15041182 | K104: =SUM(K102/K21)*100% -> 0.11217658 | N104: =SUM(N102/N21)*100% -> 0.10833879
A108: Other Income
B110: Gain on Sale or Assets | C110: 0 | D110: 0 | G110: 0 | H110: 0
B111: State Income Tax | C111: 0 | D111: 0 | G111: -15675.02 | H111: 0 | K111: -5000
B112: Rebate Income | C112: 0 | D112: 0 | G112: 9775.5 | H112: 0 | K112: 120000
B113: Interest Income | C113: 18368.49 | D113: 0 | G113: 89971.27 | H113: 0
B114: Other Income | C114: 0.42 | D114: 0 | G114: 1053.42 | H114: 0
B116: Total Other Income: | C116: =SUM(C110:C115) -> 18368.91 | D116: =SUM(D110:D115) -> 0 | G116: =SUM(G110:G114) -> 85125.17 | H116: =SUM(H110:H115) -> 0 | K116: =SUM(K110:K115) -> 115000 | N116: =162640.76-3534.07 -> 159106.69
B118: Net Income Before Tax: | C118: =+C21+C116-C35-C86-C96 -> 2102162.2 | D118: =+D21+D116-D35-D86-D96 -> 748066.12 | G118: =+G21+G116-G35-G86-G96 -> 9746484.2 | H118: =+H21+H116-H35-H86-H96 -> 5982751 | K118: =K102-K116 -> 8859126.4 | N118: =N102+N116 -> 5387140.6 | O118: =G118-N118 -> 4359343.6
B120: Net Income: | C120: =+(C21+C116-C35-C86-C96) -> 2102162.2 | D120: =+(D21+D116-D35-D86-D96) -> 748066.12 | G120: =+(G21+G116-G35-G86-G96) -> 9746484.2 | H120: =+(H21+H116-H35-H86-H96) -> 5982751 | N120: =+(N21+N116-N35-N86-N96) -> 5387140.6 | O120: =G120-N120 -> 4359343.6
A122: Bonus Program
B124: Employee
B125: Performance Bonus Paid | K125: 4487064 | N125: 59258.1 | O125: =N125-G125 -> 59258.1
G126: 0
B127: Insurance | G127: 0
B128: Performance Bonus Payable
B130: Net Inc. after Bonus Program | G130: =SUM(G120-G124-G125-G126-G127-G128) -> 9746484.2 | H130: =G130/G21 -> 0.15173708 | K130: =K102-K125 -> 4487062.4 | N130: =N120-N125 -> 5327882.5 | O130: =G130-N130 -> 4418601.7 | P130: =N130/N21 -> 0.11040792
B132: Tax Liability on Net Income | K132: 1838377.1
B134: Net Inc. after Bonus, Tax Liab | G134: =SUM(G130-G132) -> 9746484.2 | K134: =SUM(K130-K132) -> 2648685.3
B137: Total 2025 Tax Liability- as Distributions | G137: 1639195.6 | H137: Est based on Bill's CPA estimated tax payments
B138: 2026 Q-1 Distributions | H138: 459594.28 | I138: 45764
B139: 2026 Q-2 Distributions | H139: =773442.23-459594 -> 313848.23 | I139: 45823
B140: 2026 Q-3 Distributions | H140: 0 | I140: 45915
B141: 2026 Q-4 Distributions | H141: 0 | I141: 45672
B142: 2025 Dividend Pyment
B144: Net Inc. after Bonus, Tax Liab | G144: =G134 -> 9746484.2
B146: % Net Income after Ext. Exp and Bonus Program | G146: =SUM(G144/G21)*100% -> 0.15173708

Sheet August 2026 - Over Under Report
A6: Over/Under Billings - August 31, 2026 | P6: NEW CONTRACT ASSET/LIABILITY ENTRY
P7: ADJUSTMENT TO NET | Y7: 23022 | Z7: 19646.46 | AA7: Dr
P8: CONTRACT ASSET AND | Q8: Retainage from
A9: Job# | C9: Costs | D9: / | E9: Budget | F9: = % | G9: X | H9: Contract | I9: = | J9: Earned | K9: - | L9: Billed | M9: = | N9: Over/Under | P9: CONTRACT LIABILITY | Q9: AR Aging | Y9: 14220
A11: 10120 - 10120 - Waller Creek | C11: 13012238 | E11: 13081470 | F11: =+IF(E11>0,ROUND((100*C11)/E11,2),0) -> 99.47 | H11: 15374369 | J11: =+IF(E11>0,ROUND(H11*F11/100,2),0) -> 15292885 | L11: 15374369 | N11: =+IF(E11>0,J11-L11,0) -> -81484.16 | P11: =IF(N11<0,IF(-N11<Q11,N11,-Q11),0) -> -81484.16 | Q11: ='August 2026 -AR Aging'!G32 -> 1537436.9
A12: 10123 - 10123 - 400 Central* | C12: 23071770 | E12: 23071770 | F12: =+IF(E12>0,ROUND((100*C12)/E12,2),0) -> 100 | H12: 26422594 | J12: =+IF(E12>0,ROUND(H12*F12/100,2),0) -> 26422594 | L12: 26382590 | N12: =+IF(E12>0,J12-L12,0) -> 40003.2 | P12: =IF(N12<0,IF(-N12<Q12,N12,-Q12),0) -> 0 | Q12: ='August 2026 -AR Aging'!G38 -> 0
A13: 10128 - 1000 First Avenue Apartments | C13: 7238034.2 | E13: 7238034.2 | F13: =+IF(E13>0,ROUND((100*C13)/E13,2),0) -> 100 | H13: 9863898.7 | J13: =+IF(E13>0,ROUND(H13*F13/100,2),0) -> 9863898.7 | L13: 9868777.9 | N13: =+IF(E13>0,J13-L13,0) -> -4879.22 | P13: =IF(N13<0,IF(-N13<Q13,N13,-Q13),0) -> -4879.22 | Q13: ='August 2026 -AR Aging'!G53 -> 47413.81
A14: 10130 - 10130 - Art House Condominiums | C14: 11018134 | E14: 11017873 | F14: =+IF(E14>0,ROUND((100*C14)/E14,2),0) -> 100 | H14: 15546324 | J14: =+IF(E14>0,ROUND(H14*F14/100,2),0) -> 15546324 | L14: 15547951 | N14: =+IF(E14>0,J14-L14,0) -> -1627.43 | P14: =IF(N14<0,IF(-N14<Q14,N14,-Q14),0) -> -1627.43 | Q14: ='August 2026 -AR Aging'!G59 -> 1627.43
A15: 10132 - 10132 - Fairfield Ave | C15: 262643.09 | E15: 5076190.6 | F15: =+IF(E15>0,ROUND((100*C15)/E15,2),0) -> 5.17 | H15: 6295775.3 | J15: =+IF(E15>0,ROUND(H15*F15/100,2),0) -> 325491.58 | N15: =+IF(E15>0,J15-L15,0) -> 325491.58 | P15: =IF(N15<0,IF(-N15<Q15,N15,-Q15),0) -> 0
A16: 10135 - 10135 - 3rd & 3rd | C16: 4932904.3 | E16: 6188300 | F16: =+IF(E16>0,ROUND((100*C16)/E16,2),0) -> 79.71 | H16: 7318353.5 | J16: =+IF(E16>0,ROUND(H16*F16/100,2),0) -> 5833459.6 | L16: 7074613.5 | N16: =+IF(E16>0,J16-L16,0) -> -1241153.9 | P16: =IF(N16<0,IF(-N16<Q16,N16,-Q16),0) -> -707461.34 | Q16: ='August 2026 -AR Aging'!G80 -> 707461.34
A17: 10141 - 10141 Encore | C17: 11729121 | E17: 12455595 | F17: =+IF(E17>0,ROUND((100*C17)/E17,2),0) -> 94.17 | H17: 15234099 | J17: =+IF(E17>0,ROUND(H17*F17/100,2),0) -> 14345951 | L17: 15207629 | N17: =+IF(E17>0,J17-L17,0) -> -861677.91 | P17: =IF(N17<0,IF(-N17<Q17,N17,-Q17),0) -> 0 | Q17: ='August 2026 -AR Aging'!G101 -> 0
A18: 10142 - 10142 - Jacksonville Shipyards | C18: 24255357 | E18: 37509647 | F18: =+IF(E18>0,ROUND((100*C18)/E18,2),0) -> 64.66 | H18: 42437799 | J18: =+IF(E18>0,ROUND(H18*F18/100,2),0) -> 27440281 | L18: 30946661 | N18: =+IF(E18>0,J18-L18,0) -> -3506380.3 | P18: =IF(N18<0,IF(-N18<Q18,N18,-Q18),0) -> -3094666.1 | Q18: ='August 2026 -AR Aging'!G128 -> 3094666.1
A19: 10143 - 10143 MetWest | C19: 7955785.9 | E19: 7944692 | F19: =+IF(E19>0,ROUND((100*C19)/E19,2),0) -> 100.14 | H19: 9738808.3 | J19: =+IF(E19>0,ROUND(H19*F19/100,2),0) -> 9752442.7 | L19: 9646072.3 | N19: =+IF(E19>0,J19-L19,0) -> 106370.37 | P19: =IF(N19<0,IF(-N19<Q19,N19,-Q19),0) -> 0 | Q19: ='August 2026 -AR Aging'!G143 -> 0
A20: 10147 - 10147 Jordan House | C20: 446832.4 | E20: 452457 | F20: =+IF(E20>0,ROUND((100*C20)/E20,2),0) -> 98.76 | H20: 700547 | J20: =+IF(E20>0,ROUND(H20*F20/100,2),0) -> 691860.22 | L20: 700547 | N20: =+IF(E20>0,J20-L20,0) -> -8686.78 | P20: =IF(N20<0,IF(-N20<Q20,N20,-Q20),0) -> 0 | Q20: ='August 2026 -AR Aging'!G149 -> 0
A21: 10148 - 10148-Hilton Repairs Conrad* | C21: 42599.72 | E21: 42599.72 | F21: =+IF(E21>0,ROUND((100*C21)/E21,2),0) -> 100 | H21: 26175 | J21: =+IF(E21>0,ROUND(H21*F21/100,2),0) -> 26175 | L21: 29160 | N21: =+IF(E21>0,J21-L21,0) -> -2985 | P21: =IF(N21<0,IF(-N21<Q21,N21,-Q21),0) -> 0
A22: 10152 - 10152 - Westin Cocoa Beach* | C22: 13140128 | E22: 18458300 | F22: =+IF(E22>0,ROUND((100*C22)/E22,2),0) -> 71.19 | H22: 20377781 | J22: =+IF(E22>0,ROUND(H22*F22/100,2),0) -> 14506942 | L22: 16052244 | N22: =+IF(E22>0,J22-L22,0) -> -1545301.8 | P22: =IF(N22<0,IF(-N22<Q22,N22,-Q22),0) -> -1545301.8 | Q22: ='August 2026 -AR Aging'!G171 -> 1607288.3
A23: 10156 - 10156 - Encore NTMC | C23: 458152.23 | E23: 464616.02 | F23: =+IF(E23>0,ROUND((100*C23)/E23,2),0) -> 98.61 | H23: 548180.28 | J23: =+IF(E23>0,ROUND(H23*F23/100,2),0) -> 540560.57 | L23: 548180.29 | N23: =+IF(E23>0,J23-L23,0) -> -7619.72 | P23: =IF(N23<0,IF(-N23<Q23,N23,-Q23),0) -> -7619.72 | Q23: ='August 2026 -AR Aging'!G188 -> 54818.03
A24: 10158 - 10158 - Stephens Residence | C24: 72050.4 | E24: 420800 | F24: =+IF(E24>0,ROUND((100*C24)/E24,2),0) -> 17.12 | H24: 526000 | J24: =+IF(E24>0,ROUND(H24*F24/100,2),0) -> 90051.2 | L24: 261000 | N24: =+IF(E24>0,J24-L24,0) -> -170948.8 | P24: =IF(N24<0,IF(-N24<Q24,N24,-Q24),0) -> -13050 | Q24: ='August 2026 -AR Aging'!G194 -> 13050
A25: 10159 - 10159- Roberts Residence | C25: 542572.99 | E25: 540556.99 | F25: =+IF(E25>0,ROUND((100*C25)/E25,2),0) -> 100.37 | H25: 587000 | J25: =+IF(E25>0,ROUND(H25*F25/100,2),0) -> 589171.9 | L25: 587000 | N25: =+IF(E25>0,J25-L25,0) -> 2171.9 | P25: =IF(N25<0,IF(-N25<Q25,N25,-Q25),0) -> 0
A26: 10162 - 10162-Edition Hotel | C26: 143961.65 | E26: 152395 | F26: =+IF(E26>0,ROUND((100*C26)/E26,2),0) -> 94.47 | H26: 90494 | J26: =+IF(E26>0,ROUND(H26*F26/100,2),0) -> 85489.68 | L26: 90494 | N26: =+IF(E26>0,J26-L26,0) -> -5004.32
A27: 10163 - Building C Retail Center | C27: 606053.58 | E27: 804600 | F27: =+IF(E27>0,ROUND((100*C27)/E27,2),0) -> 75.32 | H27: 1064299 | J27: =+IF(E27>0,ROUND(H27*F27/100,2),0) -> 801630.01 | L27: 1060299 | N27: =+IF(E27>0,J27-L27,0) -> -258668.99 | P27: =IF(N27<0,IF(-N27<Q27,N27,-Q27),0) -> -106029.9 | Q27: ='August 2026 -AR Aging'!G204 -> 106029.9
A28: 10164 - SMC Tampa Reno | C28: 6507.94 | E28: 20600 | F28: =+IF(E28>0,ROUND((100*C28)/E28,2),0) -> 31.59 | H28: 9473.76 | J28: =+IF(E28>0,ROUND(H28*F28/100,2),0) -> 2992.76 | L28: 9473.76 | N28: -1576.26
A29: 10165 - Ravaudage Parking #1 | C29: 3175.71 | E29: 5520 | F29: =+IF(E29>0,ROUND((100*C29)/E29,2),0) -> 57.53 | H29: 8275 | J29: =+IF(E29>0,ROUND(H29*F29/100,2),0) -> 4760.61 | L29: 8275 | N29: =+IF(E29>0,J29-L29,0) -> -3514.39 | P29: =IF(N29<0,IF(-N29<Q29,N29,-Q29),0) -> 0
A30: 10166 - Stratfford Artisan Lakes | E30: 10000 | F30: =+IF(E30>0,ROUND((100*C30)/E30,2),0) -> 0 | H30: 14687.87 | J30: =+IF(E30>0,ROUND(H30*F30/100,2),0) -> 0 | L30: 14687.87 | N30: =+IF(E30>0,J30-L30,0) -> -14687.87 | P30: =IF(N30<0,IF(-N30<Q30,N30,-Q30),0) -> 0
A31: 10167 - 10167 - Ritz Residences North Tower | C31: 6798524.5 | E31: 12512221 | F31: =+IF(E31>0,ROUND((100*C31)/E31,2),0) -> 54.34 | H31: 14604901 | J31: =+IF(E31>0,ROUND(H31*F31/100,2),0) -> 7936303.3 | L31: 10178644 | N31: =+IF(E31>0,J31-L31,0) -> -2242340.9 | P31: =IF(N31<0,IF(-N31<Q31,N31,-Q31),0) -> -1018289.3 | Q31: ='August 2026 -AR Aging'!G224 -> 1018289.3
A32: 10170 - 10170 - Miami Freedom Park | C32: 30782.3 | E32: 56300 | F32: =+IF(E32>0,ROUND((100*C32)/E32,2),0) -> 54.68 | H32: 77405 | J32: =+IF(E32>0,ROUND(H32*F32/100,2),0) -> 42325.05 | L32: 77405 | N32: =+IF(E32>0,J32-L32,0) -> -35079.95 | P32: =IF(N32<0,IF(-N32<Q32,N32,-Q32),0) -> 0 | Q32: ='August 2026 -AR Aging'!G230 -> 0
A33: 10171 - 10171 - Boulanger Drywall* | C33: 154636.83 | E33: 154636.83 | F33: =+IF(E33>0,ROUND((100*C33)/E33,2),0) -> 100 | H33: 0 | J33: =+IF(E33>0,ROUND(H33*F33/100,2),0) -> 0 | L33: 209987.44 | N33: -209987.44
A34: 10173 - 10173 - Retail Center B | C34: 200354.46 | E34: 489781 | F34: =+IF(E34>0,ROUND((100*C34)/E34,2),0) -> 40.91 | H34: 633270 | J34: =+IF(E34>0,ROUND(H34*F34/100,2),0) -> 259070.76 | L34: 592020 | N34: =+IF(E34>0,J34-L34,0) -> -332949.24 | P34: =IF(N34<0,IF(-N34<Q34,N34,-Q34),0) -> -59202 | Q34: ='August 2026 -AR Aging'!G239 -> 59202
A35: 10174 - 10174 - Retail Center D | C35: 762924.71 | E35: 1019540 | F35: =+IF(E35>0,ROUND((100*C35)/E35,2),0) -> 74.83 | H35: 1269617 | J35: =+IF(E35>0,ROUND(H35*F35/100,2),0) -> 950054.4 | L35: 1264617 | N35: =+IF(E35>0,J35-L35,0) -> -314562.6 | P35: =IF(N35<0,IF(-N35<Q35,N35,-Q35),0) -> -126461.7 | Q35: ='August 2026 -AR Aging'!G250 -> 126461.7
A36: 10175 - 10175 -Totum Market | C36: 193714.22 | E36: 200000 | F36: =+IF(E36>0,ROUND((100*C36)/E36,2),0) -> 96.86 | H36: 230000 | J36: =+IF(E36>0,ROUND(H36*F36/100,2),0) -> 222778 | L36: 230000 | N36: =+IF(E36>0,J36-L36,0) -> -7222 | P36: =IF(N36<0,IF(-N36<Q36,N36,-Q36),0) -> -7222 | Q36: ='August 2026 -AR Aging'!G262 -> 23000
A37: 10176 - 10176 -The Avery* | C37: 238084.35 | E37: 819967 | F37: =+IF(E37>0,ROUND((100*C37)/E37,2),0) -> 29.04 | H37: 967213.66 | J37: =+IF(E37>0,ROUND(H37*F37/100,2),0) -> 280878.85 | L37: 88375 | N37: =+IF(E37>0,J37-L37,0) -> 192503.85 | P37: =IF(N37<0,IF(-N37<Q37,N37,-Q37),0) -> 0 | Q37: ='August 2026 -AR Aging'!G268 -> 8837.5
A38: 10178 - 10178 - Retail A* | C38: 523996.16 | E38: 1074230 | F38: =+IF(E38>0,ROUND((100*C38)/E38,2),0) -> 48.78 | H38: 1350435 | J38: =+IF(E38>0,ROUND(H38*F38/100,2),0) -> 658742.19 | L38: 1338800 | N38: =+IF(E38>0,J38-L38,0) -> -680057.81 | P38: =IF(N38<0,IF(-N38<Q38,N38,-Q38),0) -> -133880 | Q38: ='August 2026 -AR Aging'!G276 -> 133880
A39: 10179 - 10179 - Retail E | C39: 332369.79 | E39: 993530 | F39: =+IF(E39>0,ROUND((100*C39)/E39,2),0) -> 33.45 | H39: 1329537 | J39: =+IF(E39>0,ROUND(H39*F39/100,2),0) -> 444730.13 | L39: 1236800 | N39: =+IF(E39>0,J39-L39,0) -> -792069.87 | P39: =IF(N39<0,IF(-N39<Q39,N39,-Q39),0) -> -123680 | Q39: ='August 2026 -AR Aging'!G284 -> 123680
A40: 10180 - 10180 - Retail F* | C40: 72644.86 | E40: 396560 | F40: =+IF(E40>0,ROUND((100*C40)/E40,2),0) -> 18.32 | H40: 495700 | J40: =+IF(E40>0,ROUND(H40*F40/100,2),0) -> 90812.24 | L40: 491700 | N40: =+IF(E40>0,J40-L40,0) -> -400887.76 | P40: =IF(N40<0,IF(-N40<Q40,N40,-Q40),0) -> -49170 | Q40: ='August 2026 -AR Aging'!G291 -> 49170
A41: 10181 - 10181 - PCL Civil Office | C41: 275575.92 | E41: 275576 | F41: =+IF(E41>0,ROUND((100*C41)/E41,2),0) -> 100 | H41: 350131.35 | J41: =+IF(E41>0,ROUND(H41*F41/100,2),0) -> 350131.35 | L41: 350131.35 | N41: =+IF(E41>0,J41-L41,0) -> 0 | P41: =IF(N41<0,IF(-N41<Q41,N41,-Q41),0) -> 0 | Q41: ='August 2026 -AR Aging'!G303 -> 0
A42: 10182 - Disney Beach Club Ext Rehab | C42: 1592963.5 | E42: 1566743 | F42: =+IF(E42>0,ROUND((100*C42)/E42,2),0) -> 101.67 | H42: 2383197.3 | J42: =+IF(E42>0,ROUND(H42*F42/100,2),0) -> 2422996.7 | L42: 2383197.3 | N42: =+IF(E42>0,J42-L42,0) -> 39799.4 | P42: =IF(N42<0,IF(-N42<Q42,N42,-Q42),0) -> 0 | Q42: ='August 2026 -AR Aging'!G316 -> 238319.74
A43: 10184 - Project LB Disney* | C43: 1288842.6 | E43: 16424550 | F43: =+IF(E43>0,ROUND((100*C43)/E43,2),0) -> 7.85 | H43: 19323000 | J43: =+IF(E43>0,ROUND(H43*F43/100,2),0) -> 1516855.5 | N43: =+IF(E43>0,J43-L43,0) -> 1516855.5 | P43: =IF(N43<0,IF(-N43<Q43,N43,-Q43),0) -> 0
A44: 10185 - 10185 - FSJ Members Club | C44: 139.52 | E44: 176312 | F44: =+IF(E44>0,ROUND((100*C44)/E44,2),0) -> 0.08 | H44: 187557 | J44: =+IF(E44>0,ROUND(H44*F44/100,2),0) -> 150.05 | N44: =+IF(E44>0,J44-L44,0) -> 150.05 | P44: =IF(N44<0,IF(-N44<Q44,N44,-Q44),0) -> 0
A45: 10186 - Straticon - 4 Seasons Custom* | C45: 210031.39 | E45: 3199314 | F45: =+IF(E45>0,ROUND((100*C45)/E45,2),0) -> 6.56 | H45: 3787250 | J45: =+IF(E45>0,ROUND(H45*F45/100,2),0) -> 248443.6 | L45: 394952.34 | N45: =+IF(E45>0,J45-L45,0) -> -146508.74 | P45: =IF(N45<0,IF(-N45<Q45,N45,-Q45),0) -> -7166.58 | Q45: ='August 2026 -AR Aging'!G324 -> 7166.58
A46: 10187 - 10187 - Ritz Misc Work* | C46: 4453.46 | E46: 15000 | F46: =+IF(E46>0,ROUND((100*C46)/E46,2),0) -> 29.69 | H46: 37384.09 | J46: =+IF(E46>0,ROUND(H46*F46/100,2),0) -> 11099.34 | L46: 37384.09 | N46: =+IF(E46>0,J46-L46,0) -> -26284.75 | P46: =IF(N46<0,IF(-N46<Q46,N46,-Q46),0) -> 0
A47: 10188 - Law School Villiage | C47: 52.32 | E47: 3786750 | F47: =+IF(E47>0,ROUND((100*C47)/E47,2),0) -> 0 | H47: 4455000 | J47: =+IF(E47>0,ROUND(H47*F47/100,2),0) -> 0 | N47: =+IF(E47>0,J47-L47,0) -> 0 | P47: =IF(N47<0,IF(-N47<Q47,N47,-Q47),0) -> 0
A48: 10189 - 10189- Straticon Misc Work* | C48: 42701.15 | E48: 42701.15 | F48: =+IF(E48>0,ROUND((100*C48)/E48,2),0) -> 100 | H48: 46445.4 | J48: =+IF(E48>0,ROUND(H48*F48/100,2),0) -> 46445.4 | L48: 46445.4 | N48: =+IF(E48>0,J48-L48,0) -> 0 | P48: =IF(N48<0,IF(-N48<Q48,N48,-Q48),0) -> 0
A49: 10190 - 10190 - Bluffs Apartments | C49: 26453.45 | E49: 8275600 | F49: =+IF(E49>0,ROUND((100*C49)/E49,2),0) -> 0.32 | H49: 9685828 | J49: =+IF(E49>0,ROUND(H49*F49/100,2),0) -> 30994.65 | N49: =+IF(E49>0,J49-L49,0) -> 30994.65 | P49: =IF(N49<0,IF(-N49<Q49,N49,-Q49),0) -> 0
A50: 10191 - 10191 - Macon | C50: 2160 | E50: 2160 | F50: =+IF(E50>0,ROUND((100*C50)/E50,2),0) -> 100 | J50: =+IF(E50>0,ROUND(H50*F50/100,2),0) -> 0 | N50: =+IF(E50>0,J50-L50,0) -> 0 | P50: =IF(N50<0,IF(-N50<Q50,N50,-Q50),0) -> 0
A51: 10192 - 10192 - Druid Rd* | C51: 6764.22 | E51: 99461 | F51: =+IF(E51>0,ROUND((100*C51)/E51,2),0) -> 6.8 | H51: 117013 | J51: =+IF(E51>0,ROUND(H51*F51/100,2),0) -> 7956.88 | N51: =+IF(E51>0,J51-L51,0) -> 7956.88 | P51: =IF(N51<0,IF(-N51<Q51,N51,-Q51),0) -> 0
A52: 10193 - 10193 - Retail G | C52: 153205.24 | E52: 1495200 | F52: =+IF(E52>0,ROUND((100*C52)/E52,2),0) -> 10.25 | H52: 1869000 | J52: =+IF(E52>0,ROUND(H52*F52/100,2),0) -> 191572.5 | L52: 673500 | N52: =+IF(E52>0,J52-L52,0) -> -481927.5 | P52: =IF(N52<0,IF(-N52<Q52,N52,-Q52),0) -> -67350 | Q52: ='August 2026 -AR Aging'!G330 -> 67350
A53: 10194 - 10194 - Vehicle Fortress PH II | C53: 9804.79 | E53: 562785 | F53: =+IF(E53>0,ROUND((100*C53)/E53,2),0) -> 1.74 | H53: 700000.38 | J53: =+IF(E53>0,ROUND(H53*F53/100,2),0) -> 12180.01 | N53: =+IF(E53>0,J53-L53,0) -> 12180.01 | P53: =IF(N53<0,IF(-N53<Q53,N53,-Q53),0) -> 0
A54: 10195 - 10195 - Level 7 Encore | C54: 174292.16 | E54: 840250 | F54: =+IF(E54>0,ROUND((100*C54)/E54,2),0) -> 20.74 | H54: 965000 | J54: =+IF(E54>0,ROUND(H54*F54/100,2),0) -> 200141 | L54: 343400 | N54: =+IF(E54>0,J54-L54,0) -> -143259 | P54: =IF(N54<0,IF(-N54<Q54,N54,-Q54),0) -> -34340 | Q54: ='August 2026 -AR Aging'!G339 -> 34340
A55: 10196 - 10196 - TGH USF | C55: 74444.23 | E55: 1222100 | F55: =+IF(E55>0,ROUND((100*C55)/E55,2),0) -> 6.09 | H55: 1501296 | J55: =+IF(E55>0,ROUND(H55*F55/100,2),0) -> 91428.93 | N55: =+IF(E55>0,J55-L55,0) -> 91428.93 | P55: =IF(N55<0,IF(-N55<Q55,N55,-Q55),0) -> 0
A56: 10197 - 10197 - Osceola PD | C56: 53.88 | E56: 33384 | F56: =+IF(E56>0,ROUND((100*C56)/E56,2),0) -> 0.16 | H56: 39275 | J56: =+IF(E56>0,ROUND(H56*F56/100,2),0) -> 62.84 | N56: =+IF(E56>0,J56-L56,0) -> 62.84 | P56: =IF(N56<0,IF(-N56<Q56,N56,-Q56),0) -> 0
A57: 10198 - 10198 - Encore Carpentry | C57: 84667.75 | E57: 105000 | F57: =+IF(E57>0,ROUND((100*C57)/E57,2),0) -> 80.64 | H57: 127500.27 | J57: =+IF(E57>0,ROUND(H57*F57/100,2),0) -> 102816.22 | L57: 127500.27 | N57: =+IF(E57>0,J57-L57,0) -> -24684.05 | P57: =IF(N57<0,IF(-N57<Q57,N57,-Q57),0) -> 0
A58: 10199 - 10199 - Recurring Capital | C58: 0 | E58: 8651.52 | F58: =+IF(E58>0,ROUND((100*C58)/E58,2),0) -> 0 | H58: 8652 | J58: =+IF(E58>0,ROUND(H58*F58/100,2),0) -> 0 | L58: 8652 | N58: =+IF(E58>0,J58-L58,0) -> -8652 | P58: =IF(N58<0,IF(-N58<Q58,N58,-Q58),0) -> 0 | Q58: ='August 2026 -AR Aging'!G345 -> 0
A59: 10200 - 10200 - 275 5th St | C59: 5000 | E59: 5992500 | F59: =+IF(E59>0,ROUND((100*C59)/E59,2),0) -> 0.08 | H59: 7050000 | J59: =+IF(E59>0,ROUND(H59*F59/100,2),0) -> 5640 | N59: =+IF(E59>0,J59-L59,0) -> 5640 | P59: =IF(N59<0,IF(-N59<Q59,N59,-Q59),0) -> 0
A60: 10201 - 10201 -Beach Club PH 2 | C60: 328079.87 | E60: 365500 | F60: =+IF(E60>0,ROUND((100*C60)/E60,2),0) -> 89.76 | H60: 430000 | J60: =+IF(E60>0,ROUND(H60*F60/100,2),0) -> 385968 | N60: =+IF(E60>0,J60-L60,0) -> 385968 | P60: =IF(N60<0,IF(-N60<Q60,N60,-Q60),0) -> 0
A61: 10202 - 10202-Epcot Germany Restroom | C61: 20688.5 | E61: 23375 | F61: =+IF(E61>0,ROUND((100*C61)/E61,2),0) -> 88.51 | H61: 27500 | J61: 24222 | N61: =+IF(E61>0,J61-L61,0) -> 24222 | P61: =IF(N61<0,IF(-N61<Q61,N61,-Q61),0) -> 0
A62: 10203 - 10203 - 400 Central Remediation | C62: 698.5 | E62: 0 | F62: =+IF(E62>0,ROUND((100*C62)/E62,2),0) -> 0 | J62: 0 | N62: =+IF(E62>0,J62-L62,0) -> 0 | P62: =IF(N62<0,IF(-N62<Q62,N62,-Q62),0) -> 0
A63: 10204 - 10204 - Harry and Henry's | C63: 17876.59 | E63: 201473 | F63: =+IF(E63>0,ROUND((100*C63)/E63,2),0) -> 8.87 | H63: 237027 | J63: 0 | N63: =+IF(E63>0,J63-L63,0) -> 0 | P63: =IF(N63<0,IF(-N63<Q63,N63,-Q63),0) -> 0
A64: 10205 - 10205 - Thoroughbreds | C64: 56449.53 | E64: 326438 | F64: =+IF(E64>0,ROUND((100*C64)/E64,2),0) -> 17.29 | H64: 384045 | J64: 0 | N64: =+IF(E64>0,J64-L64,0) -> 0 | P64: =IF(N64<0,IF(-N64<Q64,N64,-Q64),0) -> 0
A65: 10127 - Project 913 - Main Hotel | C65: 11411046 | E65: 12102574 | F65: =+IF(E65>0,ROUND((100*C65)/E65,2),0) -> 94.29 | H65: 15025399 | J65: =+IF(E65>0,ROUND(H65*F65/100,2),0) -> 14167448 | L65: 14879838 | N65: =+IF(E65>0,J65-L65,0) -> -712390.02 | P65: =IF(N65<0,IF(-N65<Q65,N65,-Q65),0) -> 0
A66: 10139 - 10139 - WEC Event Center | C66: 8254477.3 | E66: 8657499.8 | F66: =+IF(E66>0,ROUND((100*C66)/E66,2),0) -> 95.34 | H66: 10896278 | J66: =+IF(E66>0,ROUND(H66*F66/100,2),0) -> 10388512 | L66: 10896278 | N66: =+IF(E66>0,J66-L66,0) -> -507766.57 | P66: =IF(N66<0,IF(-N66<Q66,N66,-Q66),0) -> 0
A67: 10168 - 10168 - WGH Building | C67: 0 | E67: 0 | F67: =+IF(E67>0,ROUND((100*C67)/E67,2),0) -> 0 | H67: 0 | J67: =+IF(E67>0,ROUND(H67*F67/100,2),0) -> 0 | L67: 3157.3 | N67: =+IF(E67>0,J67-L67,0) -> 0 | P67: =IF(N67<0,IF(-N67<Q67,N67,-Q67),0) -> 0
F68: =+IF(E68>0,ROUND((100*C68)/E68,2),0) -> 0 | J68: =+IF(E68>0,ROUND(H68*F68/100,2),0) -> 0 | P68: =IF(N68<0,IF(-N68<Q68,N68,-Q68),0) -> 0
A69: 20022 - 20022 - Hang 10* | C69: 430164.59 | E69: 430164.59 | F69: =+IF(E69>0,ROUND((100*C69)/E69,2),0) -> 100 | H69: 420218 | J69: =+IF(E69>0,ROUND(H69*F69/100,2),0) -> 420218 | L69: 420218 | N69: =+IF(E69>0,J69-L69,0) -> 0 | P69: =IF(N69<0,IF(-N69<Q69,N69,-Q69),0) -> 0
A70: 20034 - Hang 10 - Curry Ford Rd* | C70: 306283.11 | E70: 306283.11 | F70: =+IF(E70>0,ROUND((100*C70)/E70,2),0) -> 100 | H70: 331495 | J70: =+IF(E70>0,ROUND(H70*F70/100,2),0) -> 331495 | L70: 331495 | N70: =+IF(E70>0,J70-L70,0) -> 0 | P70: =IF(N70<0,IF(-N70<Q70,N70,-Q70),0) -> 0
A71: 20035 - 20035 - HPCC PH 2 - NEW 20005* | C71: 300583.04 | E71: 300583.04 | F71: =+IF(E71>0,ROUND((100*C71)/E71,2),0) -> 100 | H71: 278236.5 | J71: =+IF(E71>0,ROUND(H71*F71/100,2),0) -> 278236.5 | L71: 200645 | N71: =+IF(E71>0,J71-L71,0) -> 77591.5 | P71: =IF(N71<0,IF(-N71<Q71,N71,-Q71),0) -> 0 | Q71: ='August 2026 -AR Aging'!G351 -> 0
A72: 20041 - LM Electrical Substation* | C72: 33457.17 | E72: 33457.17 | F72: =+IF(E72>0,ROUND((100*C72)/E72,2),0) -> 100 | H72: 90143.17 | J72: =+IF(E72>0,ROUND(H72*F72/100,2),0) -> 90143.17 | L72: 90143.17 | N72: =+IF(E72>0,J72-L72,0) -> 0 | P72: =IF(N72<0,IF(-N72<Q72,N72,-Q72),0) -> 0 | Q72: ='August 2026 -AR Aging'!G357 -> 0
A73: 20042 - 20042 - City National Bank of Florida* | C73: 20835.95 | E73: 20835.95 | F73: =+IF(E73>0,ROUND((100*C73)/E73,2),0) -> 100 | H73: 26500 | J73: =+IF(E73>0,ROUND(H73*F73/100,2),0) -> 26500 | L73: 20500 | N73: =+IF(E73>0,J73-L73,0) -> 6000 | P73: =IF(N73<0,IF(-N73<Q73,N73,-Q73),0) -> 0 | Q73: ='August 2026 -AR Aging'!G363 -> 2050
A74: 20043 - Ridgeclub | C74: 3144.67 | E74: 3144.67 | F74: =+IF(E74>0,ROUND((100*C74)/E74,2),0) -> 100 | H74: 4548 | J74: =+IF(E74>0,ROUND(H74*F74/100,2),0) -> 4548 | L74: 4548 | N74: =+IF(E74>0,J74-L74,0) -> 0
A75: 20044 - 20044 - HCA | C75: 13365.45 | E75: 13365.45 | F75: =+IF(E75>0,ROUND((100*C75)/E75,2),0) -> 100 | H75: 49900 | J75: =+IF(E75>0,ROUND(H75*F75/100,2),0) -> 49900 | L75: 22000 | N75: =+IF(E75>0,J75-L75,0) -> 27900 | P75: =IF(N75<0,IF(-N75<Q75,N75,-Q75),0) -> 0 | Q75: ='August 2026 -AR Aging'!G369 -> 2200
F76: =+IF(E76>0,ROUND((100*C76)/E76,2),0) -> 0 | J76: =+IF(E76>0,ROUND(H76*F76/100,2),0) -> 0 | L76: 22000 | N76: =+IF(E76>0,J76-L76,0) -> 0 | P76: =IF(N76<0,IF(-N76<Q76,N76,-Q76),0) -> 0
A77: 20040 - 20040 - Amazon MC09* | C77: 593317.52 | E77: 593317.52 | F77: =+IF(E77>0,ROUND((100*C77)/E77,2),0) -> 100 | H77: 481089 | J77: =+IF(E77>0,ROUND(H77*F77/100,2),0) -> 481089 | L77: 481089 | N77: =+IF(E77>0,J77-L77,0) -> 0 | P77: =IF(N77<0,IF(-N77<Q77,N77,-Q77),0) -> 0
F78: =+IF(E78>0,ROUND((100*C78)/E78,2),0) -> 0 | P78: =IF(N78<0,IF(-N78<Q78,N78,-Q78),0) -> 0
F79: =+IF(E79>0,ROUND((100*C79)/E79,2),0) -> 0 | P79: =IF(N79<0,IF(-N79<Q79,N79,-Q79),0) -> 0
F80: =+IF(E80>0,ROUND((100*C80)/E80,2),0) -> 0 | P80: =IF(N80<0,IF(-N80<Q80,N80,-Q80),0) -> 0
F81: =+IF(E81>0,ROUND((100*C81)/E81,2),0) -> 0 | P81: =IF(N81<0,IF(-N81<Q81,N81,-Q81),0) -> 0
F82: =+IF(E82>0,ROUND((100*C82)/E82,2),0) -> 0 | P82: =IF(N82<0,IF(-N82<Q82,N82,-Q82),0) -> 0
F83: =+IF(E83>0,ROUND((100*C83)/E83,2),0) -> 0 | P83: =IF(N83<0,IF(-N83<Q83,N83,-Q83),0) -> 0 | R83: Other Closed Projects
B85: Totals: | C85: =SUM(C11:C84) -> 1.5398813e+08 | E85: =SUM(E11:E84) -> 2.3017483e+08 | H85: =SUM(H11:H84) -> 2.7445892e+08 | J85: =SUM(J11:J84) -> 1.8493585e+08 | L85: =SUM(L11:L84) -> 1.9685545e+08 | N85: =SUM(N11:N84) -> -11889536 | P85: =SUM(P11:P84) -> -7188881.2 | Q85: =SUM(Q11:Q84) -> 9063738.6
A87: *Budget is actual costs when costs exceed budget.
Q88: =Q85-'August 2026 -AR Aging'!G372 -> 0
A89: FL Total: | B89: =SUMIF(N11:N84,"<0") -> -14782827 | C89: =IF(B89<0,"OVER","UNDER") -> OVER
B90: =SUMIF(N11:N84,">0") -> 2893290.7 | C90: =IF(B90<0,"OVER","UNDER") -> UNDER
B91: =SUM(B89:B90) -> -11889536 | C91: =B91-N85 -> 0
B93: Liabilities | C93: Assets
B94: =SUM(B89) -> -14782827 | C94: 0
B95: =IF(B90<0,B90,0) -> 0 | C95: =IF(B90>0,B90,0) -> 2893290.7
B96: =SUM(B94:B95) -> -14782827 | C96: =SUM(C94:C95) -> 2893290.7

Sheet August 2026 -AR Aging
A6: Accounts Receivable Aging - August 31, 2026
A8: Job | B8: Invoice# | C8: Due Date | E8: Balance | F8: Retained | G8: Current | H8: 1 - 30 | I8: 31 - 60 | J8: 61 - 90 | K8: 91+ | L8: Total Due
A9: 10120 10120 - Waller Creek
B11: 2296 | C11: 10120.01 October | D11: 12/31/2026 | F11: 13398 | G11: 13398 | M11: 0
B12: 2299 | C12: 10120.02 November | D12: 12/31/2026 | F12: 23187.41 | G12: 23187.41 | M12: 0
B13: 2338 | C13: 10120 December | D13: 12/31/2026 | F13: 7895.9 | G13: 7895.9 | M13: 0
B14: 2357 | C14: 10120 January | D14: 12/31/2026 | F14: 62501.6 | G14: 62501.6 | M14: 0
B15: 2412 | C15: 10120 February | D15: 12/31/2026 | F15: 161525.62 | G15: 161525.62 | M15: 0
B16: 2413 | C16: 10120 March | D16: 12/31/2026 | F16: 121182.19 | G16: 121182.19 | M16: 0
B17: 2427 | C17: 10120 April | D17: 12/31/2026 | F17: 177312.62 | G17: 177312.62 | M17: 0
B18: 2445 | C18: 10120 May | D18: 12/31/2026 | F18: 109200.05 | G18: 109200.05 | M18: 0
B19: 2460 | C19: 10120 June | D19: 12/31/2026 | F19: 204970.17 | G19: 204970.17 | M19: 0
B20: 2486 | C20: 10120 July | D20: 12/31/2026 | F20: 147771.55 | G20: 147771.55 | M20: 0
B21: 2510 | C21: 10120 August | D21: 12/31/2026 | F21: 175869.58 | G21: 175869.58 | M21: 0
B22: 2532 | C22: 10120 September | D22: 12/31/2026 | F22: 169230.79 | G22: 169230.79 | M22: 0
... B29: 2735 | C29: 10120 May | D29: 12/31/2026 | F29: 2179.26 | G29: 2179.26 | M29: 0
B30: 2779 | C30: 10120 JULY | D30: 12/31/2026 | F30: 105000 | G30: 10500 | H30: 94500 | M30: 94500
E32: Job Totals: | F32: 1631936.9 | G32: 1537436.9 | H32: 94500 | I32: 0 | J32: 0 | K32: 0 | L32: 0 | M32: 94500
A34: 10123 10123 - 400 Central
B36: 2744 | C36: 10123 June | D36: 06/30/2026 | F36: -6868.32 | G36: 0 | K36: -6868.32 | M36: -6868.32
E38: Job Totals: | F38: -6868.32 | G38: 0 | H38: 0 | I38: 0 | J38: 0 | K38: -6868.32 | L38: 0 | M38: -6868.32
A40: 10128 1000 First Avenue Apartments
B42: 2428 | C42: 10128 April | D42: 01/31/2026 | F42: 13682.61 | G42: 13682.61 | M42: 0
B43: 2443 | C43: 10128 May | D43: 01/31/2026 | F43: 3697.83 | G43: 3697.83 | M43: 0
B44: 2491 | C44: 10128 July | D44: 01/31/2026 | F44: 10060.89 | G44: 10060.89 | M44: 0
B45: 2498 | C45: 10128 August Rev1 | D45: 01/31/2026 | F45: 7312.94 | G45: 7312.94 | M45: 0
B46: 2537 | C46: 10128 September | D46: 01/31/2026 | F46: 2254.06 | G46: 2254.06 | M46: 0
B47: 2551 | C47: 10128 | D47: 01/31/2026 | F47: -19774.76 | G47: 0 | L47: -19774.76 | M47: -19774.76
B48: 2589 | C48: 10128 November | D48: 01/31/2026 | F48: 3270.87 | G48: 3270.87 | M48: 0
B49: 2605 | C49: 10128 Dec | D49: 01/31/2026 | F49: 5135.66 | G49: 5135.65 | L49: 0.01 | M49: 0.01
B50: 2617 | C50: 10128 Dec CO | D50: 01/31/2026 | F50: 1733.83 | G50: 1733.83 | M50: 0
B51: 2618 | C51: 10128 Dec to Bill Ou | D51: 01/30/2026 | F51: 2651.3 | G51: 265.13 | L51: 2386.17 | M51: 2386.17
E53: Job Totals: | F53: 30025.23 | G53: 47413.81 | H53: 0 | I53: 0 | J53: 0 | K53: 0 | L53: -17388.58 | M53: -17388.58
A55: 10130 10130 - Art House Condominiums
B57: 2676 | C57: 10130 | D57: 03/16/2026 | F57: 1627.43 | G57: 1627.43 | M57: 0
E59: Job Totals: | F59: 1627.43 | G59: 1627.43 | H59: 0 | I59: 0 | J59: 0 | K59: 0 | L59: 0 | M59: 0
A61: 10135 10135 - 3rd & 3rd
B63: 2421 | C63: 10135 April | D63: 04/22/2025 | F63: 5900 | G63: 5900 | M63: 0
B64: 2462 | C64: 10135 June | D64: 06/22/2025 | F64: 8955.6 | G64: 8955.6 | M64: 0
B65: 2499 | C65: 10135 July | D65: 08/01/2025 | F65: 28070.9 | G65: 28070.9 | M65: 0
B66: 2506 | C66: 10135 August | D66: 08/31/2025 | F66: 14480 | G66: 14480 | M66: 0
B67: 2535 | C67: 10135 Sedptember | D67: 09/30/2025 | F67: 17592.5 | G67: 17592.5 | M67: 0
B68: 2559 | C68: 10135 October | D68: 10/30/2025 | F68: 65296.56 | G68: 65296.56 | M68: 0
B69: 2585 | C69: 10135 November | D69: 11/29/2025 | F69: 41218.73 | G69: 41218.73 | M69: 0
B70: 2609 | C70: 10135 December | D70: 12/29/2025 | F70: 45496 | G70: 45496 | M70: 0
B71: 2647 | C71: 10135 January | D71: 01/28/2026 | F71: 72652.17 | G71: 72652.17 | M71: 0
B72: 2648 | C72: 10135 February | D72: 02/27/2026 | F72: 64862 | G72: 64862 | M72: 0
B73: 2677 | C73: 10135 March | D73: 03/29/2026 | F73: 81165.28 | G73: 81165.28 | M73: 0
B74: 2701 | C74: 10135 April | D74: 04/28/2026 | F74: 67931.25 | G74: 67931.25 | M74: 0
... B76: 2729 | C76: 10135 June | D76: 07/20/2026 | F76: 66041.57 | G76: 66041.57 | M76: 0
B77: 2755 | C77: 10135 July | D77: 07/28/2026 | F77: 366666.98 | G77: 36666.7 | J77: 330000.28 | M77: 330000.28
B78: 2783 | C78: 10135 August | D78: 08/27/2026 | F78: 184722.73 | G78: 18472.28 | I78: 166250.45 | M78: 166250.45
E80: Job Totals: | F80: 1203712.1 | G80: 707461.34 | H80: 0 | I80: 166250.45 | J80: 330000.28 | K80: 0 | L80: 0 | M80: 496250.73
A82: 10141 10141 Encore
B84: 2388 | C84: 10141 March | D84: 12/31/2026 | F84: 3474.9 | G84: 0 | H84: 3474.9 | M84: 3474.9
B85: 2430 | C85: 10141 April | D85: 12/31/2026 | F85: 14725.35 | G85: 0 | H85: 14725.35 | M85: 14725.35
B86: 2442 | C86: 10141 May | D86: 12/31/2026 | F86: 5586.05 | G86: 0 | H86: 5586.05 | M86: 5586.05
B87: 2464 | C87: 10141 June | D87: 12/31/2026 | F87: 14925.28 | G87: 0 | H87: 14925.28 | M87: 14925.28
B88: 2476 | C88: 10141 July | D88: 12/31/2026 | F88: 29578.91 | G88: 0 | H88: 29578.91 | M88: 29578.91
B89: 2508 | C89: 10141 August | D89: 12/31/2026 | F89: 30075.12 | G89: 0 | H89: 30075.12 | M89: 30075.12
B90: 2536 | C90: 10141 September | D90: 12/31/2026 | F90: 158236.19 | G90: 0 | H90: 158236.19 | M90: 158236.19
B91: 2560 | C91: 10141 October | D91: 12/31/2026 | F91: 201762.48 | G91: 0 | H91: 201762.48 | M91: 201762.48
B92: 2586 | C92: 10141 November | D92: 12/31/2026 | F92: 240223.86 | G92: 0 | H92: 240223.86 | M92: 240223.86
B93: 2610 | C93: 10141 December | D93: 12/31/2026 | F93: 208742.27 | G93: 0 | H93: 208742.27 | M93: 208742.27
B94: 2649 | C94: 10141 January | D94: 12/31/2026 | F94: 219826.1 | G94: 0 | H94: 219826.1 | M94: 219826.1
B95: 2653 | C95: 10141 February | D95: 12/31/2026 | F95: 158644.25 | G95: 0 | H95: 158644.25 | M95: 158644.25
... B99: 2758 | C99: 10141 June | D99: 12/31/2026 | F99: 7480.88 | G99: 0 | H99: 7480.88 | M99: 7480.88
E101: Job Totals: | F101: 1520763 | G101: 0 | H101: 1520763 | I101: 0 | J101: 0 | K101: 0 | L101: 0 | M101: 1520763
A103: 10142 10142 - Jacksonville Shipyards
B105: 2306 | C105: 10142.01 November | D105: 09/11/2026 | F105: 28200 | G105: 28200 | M105: 0
B106: 2340 | C106: 10142.02 December | D106: 09/11/2026 | F106: 8650 | G106: 8650 | M106: 0
B107: 2379 | C107: 10142.03 January | D107: 09/11/2026 | F107: 30350 | G107: 30350 | M107: 0
B108: 2380 | C108: 10142.04 February | D108: 09/11/2026 | F108: 10300 | G108: 10300 | M108: 0
B109: 2410 | C109: 10142 March | D109: 09/11/2026 | F109: 27323.75 | G109: 27323.75 | M109: 0
B110: 2431 | C110: 10142 April | D110: 09/11/2026 | F110: 33779 | G110: 33779 | M110: 0
B111: 2448 | C111: 10142 May | D111: 09/11/2026 | F111: 51772.5 | G111: 51772.5 | M111: 0
B112: 2457 | C112: 10142 June | D112: 09/11/2026 | F112: 100221 | G112: 100221 | M112: 0
B113: 2490 | C113: 10142 July | D113: 09/11/2026 | F113: 80941.36 | G113: 80941.36 | M113: 0
B114: 2503 | C114: 10142 August | D114: 09/11/2026 | F114: 177995.15 | G114: 177995.15 | M114: 0
B115: 2524 | C115: 10142 September | D115: 09/11/2026 | F115: 150451.25 | G115: 150451.25 | M115: 0
B116: 2561 | C116: 10142 October | D116: 09/11/2026 | F116: 264873 | G116: 264873 | M116: 0
B117: 2606 | C117: 10142 November | D117: 09/11/2026 | F117: 355957.94 | G117: 355957.93 | H117: 0.01 | M117: 0.01
B118: 2611 | C118: 10142 December | D118: 09/11/2026 | F118: 201196.48 | G118: 201196.48 | M118: 0
B119: 2634 | C119: 10142 January | D119: 09/11/2026 | F119: 117347.06 | G119: 117347.06 | M119: 0
B120: 2652 | C120: 10142 February | D120: 09/11/2026 | F120: 127968.21 | G120: 127968.21 | M120: 0
B121: 2679 | C121: 10142 March | D121: 09/11/2026 | F121: 212234.06 | G121: 212234.06 | M121: 0
B122: 2703 | C122: 10142 April | D122: 09/11/2026 | F122: 165373.28 | G122: 165373.28 | M122: 0
B123: 2720 | C123: 10142 May | D123: 09/11/2026 | F123: 249899.77 | G123: 249899.77 | M123: 0
B124: 2763 | C124: 10142 June | D124: 09/11/2026 | F124: 260239.72 | G124: 260239.72 | M124: 0
B125: 2764 | C125: 10142 July | D125: 12/31/2026 | F125: 2792611.1 | G125: 279261.11 | H125: 2513350 | M125: 2513350
B126: 2795 | C126: 10142 August | D126: 09/11/2026 | F126: 1603314.5 | G126: 160331.45 | H126: 1442983.1 | M126: 1442983.1
E128: Job Totals: | F128: 7050999.1 | G128: 3094666.1 | H128: 3956333 | I128: 0 | J128: 0 | K128: 0 | L128: 0 | M128: 3956333
A130: 10143 10143 MetWest
B132: 2419 | C132: 10143 April | D132: 09/11/2026 | F132: 5611.63 | G132: 0 | H132: 5611.63 | M132: 5611.63
B133: 2469 | C133: 10143 May | D133: 09/11/2026 | F133: 84752.29 | G133: 0 | H133: 84752.29 | M133: 84752.29
B134: 2470 | C134: 10143 June | D134: 09/11/2026 | F134: 111981.19 | G134: 0 | H134: 111981.19 | M134: 111981.19
B135: 2495 | C135: 10143 July | D135: 07/06/2026 | F135: 136069.8 | G135: 0 | J135: 136069.8 | M135: 136069.8
B136: 2502 | C136: 10143 August | D136: 09/11/2026 | F136: 149676.18 | G136: 0 | H136: 149676.18 | M136: 149676.18
B137: 2576 | C137: 10143 November | D137: 09/11/2026 | F137: 39419.66 | G137: 0 | H137: 39419.66 | M137: 39419.66
B138: 2612 | C138: 10143 December | D138: 09/11/2026 | F138: 12248.97 | G138: 0 | H138: 12248.97 | M138: 12248.97
...

Sheet Sheet1
A1: Stowell Prior Year Comparison
C2: 2026 | E2: 2025
C3: August YTD | E3: =C3 -> August YTD | G3: Var
A4: Revenue | C4: ='August 2026 - Inc. Stmt- ALL'!G21 -> 64232711 | E4: ='August 2026 - Inc. Stmt- ALL'!N21 -> 48256343 | G4: =C4-E4 -> 15976368
A6: Direct Expense | C6: ='August 2026 - Inc. Stmt- ALL'!G35 -> 52485705 | E6: ='August 2026 - Inc. Stmt- ALL'!N35 -> 41029273 | G6: =E6-C6 -> -11456432
A8: Gross Profit | C8: ='August 2026 - Inc. Stmt- ALL'!G40 -> 11747006 | E8: ='August 2026 - Inc. Stmt- ALL'!N40 -> 7227069.7 | G8: =C8-E8 -> 4519936.5
A9: Gross Profit % | C9: =C8/C4 -> 0.18288199 | E9: =E8/E4 -> 0.14976414
A11: Total Indirect Expenses | C11: ='August 2026 - Inc. Stmt- ALL'!G98 -> 2085647.1 | E11: ='August 2026 - Inc. Stmt- ALL'!N98 -> 1999035.8 | G11: =E11-C11 -> -86611.39
A12: % of Operating Income | C12: =C11/C4 -> 0.032470172 | E12: =E11/E4 -> 0.041425347
A14: Income from Operations | C14: =C8-C11 -> 9661359 | E14: =E8-E11 -> 5228033.9 | G14: =C14-E14 -> 4433325.1
A15: % of Operating Income | C15: =C14/C4 -> 0.15041182 | E15: =E14/E4 -> 0.10833879
A20: Projected 2026 vs 2025 | C20: Proj 2026 | E20: 2025 Act | G20: Var
A22: Projected Revenue | C22: 94000000 | E22: 78301875 | G22: =C22-E22 -> 15698125
A24: Direct Expense | C24: =C22*0.831 -> 78114000 | E24: 65455966 | G24: =E24-C24 -> -12658034
A26: Gross Profit | C26: =C22-C24 -> 15886000 | E26: =E22-E24 -> 12845910 | G26: =C26-E26 -> 3040090.4
A27: Gross Profit % | C27: =C26/C22 -> 0.169 | E27: =E26/E22 -> 0.16405622
A29: Total Indirect Expenses | C29: ='August 2026 - Inc. Stmt- ALL'!K98 -> 3279206.6 | E29: =8132296.75-4968706.88 -> 3163589.9 | G29: =E29-C29 -> -115616.7
A30: % of Operating Income | C30: =C29/C22 -> 0.034885176 | E30: =E29/E22 -> 0.040402479
A32: Income from Operations | C32: =C26-C29 -> 12606793 | E32: =E26-E29 -> 9682319.7 | G32: =C32-E32 -> 2924473.7
A33: % of Operating Income | C33: =C32/C22 -> 0.13411482 | E33: =E32/E22 -> 0.12365374
A35: Est Bonus Payout | C35: =E35/E26*C26 -> 6144592.3 | E35: 4968706.9 | G35: =E35-C35 -> -1175885.4
A37: Net Income from operations | C37: =C32-C35 -> 6462201.1 | E37: =E32-E35 -> 4713612.9 | G37: =C37-E37 -> 1748588.3
A38: % of Operating Income | C38: =C37/C22 -> 0.06874682 | E38: =E37/E22 -> 0.060197956

Sheet Sheet2
